LICENSE.txt
README.md
setup.cfg
setup.py
apievaluator/__init__.py
apievaluator/main.py
apievaluator.egg-info/PKG-INFO
apievaluator.egg-info/SOURCES.txt
apievaluator.egg-info/dependency_links.txt
apievaluator.egg-info/entry_points.txt
apievaluator.egg-info/requires.txt
apievaluator.egg-info/top_level.txt
apievaluator/custom_tests/AbstractTest.py
apievaluator/custom_tests/ArrayOfLength.py
apievaluator/custom_tests/Boolean.py
apievaluator/custom_tests/ObjectWithKeys.py
apievaluator/custom_tests/Positive.py
apievaluator/custom_tests/StringRegex.py
apievaluator/custom_tests/__init__.py
apievaluator/logic/Tests.py
apievaluator/logic/__init__.py